kelp/__init__.py
kelp/bucket.yml
kelp/requirements.txt
kelp/trail.yml
aws_keLP-0.0.3.dist-info/LICENSE
aws_keLP-0.0.3.dist-info/METADATA
aws_keLP-0.0.3.dist-info/WHEEL
aws_keLP-0.0.3.dist-info/entry_points.txt
aws_keLP-0.0.3.dist-info/top_level.txt
aws_keLP-0.0.3.dist-info/RECORD
