Metadata-Version: 2.1
Name: aws-keLP
Version: 0.0.3
Summary: Serverless IAM least privilege automation
Home-page: https://github.com/LamarrD/keLP
Author: LamarrD
Author-email: henry.773@osu.edu
License: MIT
Platform: UNKNOWN
Requires-Dist: boto3
